codatfiles/__init__.py
codatfiles/files.py
codatfiles/sdk.py
codatfiles/sdkconfiguration.py
codatfiles/models/__init__.py
codatfiles/models/errors/__init__.py
codatfiles/models/errors/sdkerror.py
codatfiles/models/operations/__init__.py
codatfiles/models/operations/download_files.py
codatfiles/models/operations/list_files.py
codatfiles/models/operations/upload_files.py
codatfiles/models/shared/__init__.py
codatfiles/models/shared/errormessage.py
codatfiles/models/shared/file.py
codatfiles/models/shared/security.py
codatfiles/utils/__init__.py
codatfiles/utils/retries.py
codatfiles/utils/utils.py
codat_files-0.34.0.dist-info/METADATA
codat_files-0.34.0.dist-info/WHEEL
codat_files-0.34.0.dist-info/top_level.txt
codat_files-0.34.0.dist-info/RECORD
