Metadata-Version: 2.1
Name: codat-files
Version: 0.34.0
Summary: Use Codat's Files API to upload your SMB customers' files.
Home-page: UNKNOWN
Author: Codat
License: UNKNOWN
Platform: UNKNOWN
Requires-Python: >=3.9
Requires-Dist: certifi >=2022.12.7
Requires-Dist: charset-normalizer >=2.1.1
Requires-Dist: dataclasses-json >=0.5.12
Requires-Dist: idna >=3.3
Requires-Dist: jsonpath-python >=1.0.6
Requires-Dist: marshmallow >=3.17.1
Requires-Dist: marshmallow-enum >=1.5.1
Requires-Dist: mypy-extensions >=0.4.3
Requires-Dist: packaging >=21.3
Requires-Dist: pyparsing >=3.0.9
Requires-Dist: python-dateutil >=2.8.2
Requires-Dist: requests >=2.28.1
Requires-Dist: six >=1.16.0
Requires-Dist: typing-inspect >=0.8.0
Requires-Dist: typing-extensions >=4.3.0
Requires-Dist: urllib3 >=1.26.12
Provides-Extra: dev
Requires-Dist: pylint ==2.16.2 ; extra == 'dev'
